{
  "$schema": "https://schema.management.azure.com/schemas/2019-04-01/deploymentTemplate.json#",
  "contentVersion": "1.0.0.0",
  "parameters": {
    "name": {
      "type": "string"
    },
    "displayName": {
      "type": "string"
    },
    "repositoryUrl": {
      "type": "string"
    },
    "skuTier": {
      "type": "string"
    },
    "skuTier": {
      "type": "string"
    },
    "skipGitHubactionWorkflowGeneration": {
      "type": "bool"
    }
  },
  "resources": [
    {
      "apiVersion": "2020-12-01",
      "name": "[parameters('name')]",
      "type": "Microsoft.Web/staticSites",
      "location": "[parameters('location')]",
      "tags": "[parameters('tags')]",
      "properties": {
        "kind": "string",
        "properties": {
          "repositoryUrl": "[parameters('repositoryUrl')]",
          "branch": "[parameters('branch')]",
          "buildProperties": {
            "appLocation": "[parameters('appLocation')]",
            "outputLocation": "[parameters('outputLocation')]",
            "skipGithubActionWorkflowGeneration": "[parameters('skipGitHubactionWorkflowGeneration')]"
          }
        }
      },
      "sku": {
        "tier": "[parameters('skuTier')]",
        "name": "[parameters('skuName')]"
      }
    }
  ],
  "outputs": {
    "name": {
      "type": "string",
      "value": "[parameters('name')]"
    }
  }
}
